krashemit/__init__.py
krashemit/testik.py
krashemit/algorithms/__init__.py
krashemit/algorithms/country_optimization.py
krashemit/algorithms/country_optimization_v2.py
krashemit/algorithms/country_optimization_v3.py
krashemit/algorithms/genetic_optimization.py
krashemit/algorithms/gold_digger_optimization.py
krashemit/benchmakrs/__init__.py
krashemit/benchmakrs/aggregators.py
krashemit/benchmakrs/benchmark.py
krashemit/benchmakrs/plotters.py
krashemit/benchmakrs/test_functions.py
krashemit/benchmakrs/tg.py
krashemit-1.0.5.dist-info/METADATA
krashemit-1.0.5.dist-info/WHEEL
krashemit-1.0.5.dist-info/top_level.txt
krashemit-1.0.5.dist-info/RECORD
